langchain_ocr_lib/__init__.py
langchain_ocr_lib/chains/__init__.py
langchain_ocr_lib/chains/chain.py
langchain_ocr_lib/converter/__init__.py
langchain_ocr_lib/converter/converter.py
langchain_ocr_lib/di_binding_keys/__init__.py
langchain_ocr_lib/di_binding_keys/binding_keys.py
langchain_ocr_lib/di_config.py
langchain_ocr_lib/impl/__init__.py
langchain_ocr_lib/impl/chains/__init__.py
langchain_ocr_lib/impl/chains/ocr_chain.py
langchain_ocr_lib/impl/converter/__init__.py
langchain_ocr_lib/impl/converter/image_converter.py
langchain_ocr_lib/impl/converter/pdf_converter.py
langchain_ocr_lib/impl/langfuse_manager/__init__.py
langchain_ocr_lib/impl/langfuse_manager/langfuse_manager.py
langchain_ocr_lib/impl/llms/__init__.py
langchain_ocr_lib/impl/llms/llm_factory.py
langchain_ocr_lib/impl/llms/llm_type.py
langchain_ocr_lib/impl/settings/__init__.py
langchain_ocr_lib/impl/settings/langfuse_settings.py
langchain_ocr_lib/impl/settings/language_settings.py
langchain_ocr_lib/impl/settings/llm_class_type_settings.py
langchain_ocr_lib/impl/settings/ollama_chat_settings.py
langchain_ocr_lib/impl/settings/openai_chat_settings.py
langchain_ocr_lib/impl/settings/together_ai_chat_settings.py
langchain_ocr_lib/impl/settings/vllm_chat_settings.py
langchain_ocr_lib/impl/tracers/__init__.py
langchain_ocr_lib/impl/tracers/langfuse_traced_chain.py
langchain_ocr_lib/language_mapping/language_mapping.py
langchain_ocr_lib/main.py
langchain_ocr_lib/prompt_templates/__init__.py
langchain_ocr_lib/prompt_templates/ocr_prompt.py
langchain_ocr_lib/tracers/__init__.py
langchain_ocr_lib/tracers/traced_chain.py
langchain_ocr_lib-0.4.1.dist-info/METADATA
langchain_ocr_lib-0.4.1.dist-info/WHEEL
langchain_ocr_lib-0.4.1.dist-info/entry_points.txt
langchain_ocr_lib-0.4.1.dist-info/RECORD
