Metadata-Version: 2.3
Name: langchain-ocr-lib
Version: 0.4.1
Summary: Modular, vision-LLM-powered chain to convert image and PDF documents into clean Markdown.
License: MIT
Author: Andreas Klos
Author-email: aklos@outlook.de
Requires-Python: >=3.11,<4.0
Classifier: License :: OSI Approved :: MIT License
Classifier: Programming Language :: Python :: 3
Classifier: Programming Language :: Python :: 3.11
Classifier: Programming Language :: Python :: 3.12
Classifier: Programming Language :: Python :: 3.13
Requires-Dist: deprecated (>=1.2.14,<2.0.0)
Requires-Dist: inject (>=5.2.1,<6.0.0)
Requires-Dist: langchain-community (>=0.3.19,<0.4.0)
Requires-Dist: langchain-ollama (>=0.2.0,<0.3.0)
Requires-Dist: langchain-openai (>=0.3.8,<0.4.0)
Requires-Dist: langchain-together (>=0.3.0,<0.4.0)
Requires-Dist: langfuse (>=2.59.7,<3.0.0)
Requires-Dist: openai (>=1.42.0,<2.0.0)
Requires-Dist: pdf2image (>=1.17.0,<2.0.0)
Requires-Dist: pillow (>=11.0.0,<12.0.0)
Requires-Dist: pycountry (>=24.6.1,<25.0.0)
Requires-Dist: pytest-asyncio (>=0.25.0,<0.26.0)
Requires-Dist: pyyaml (>=6.0.2,<7.0.0)
